finapi/__init__.py
finapi/api_client.py
finapi/configuration.py
finapi/rest.py
finapi/api/__init__.py
finapi/api/accounts_api.py
finapi/api/authorization_api.py
finapi/api/bank_connections_api.py
finapi/api/banks_api.py
finapi/api/categories_api.py
finapi/api/client_configuration_api.py
finapi/api/labels_api.py
finapi/api/mandator_administration_api.py
finapi/api/mocks_and_tests_api.py
finapi/api/notification_rules_api.py
finapi/api/payments_api.py
finapi/api/securities_api.py
finapi/api/transactions_api.py
finapi/api/users_api.py
finapi/api/web_forms_api.py
finapi/models/__init__.py
finapi/models/access_token.py
finapi/models/account.py
finapi/models/account_list.py
finapi/models/account_params.py
finapi/models/bad_credentials_error.py
finapi/models/bank.py
finapi/models/bank_connection.py
finapi/models/bank_connection_list.py
finapi/models/bank_connection_owner.py
finapi/models/bank_list.py
finapi/models/cash_flow.py
finapi/models/cash_flow_list.py
finapi/models/categorization_check_result.py
finapi/models/categorization_check_results.py
finapi/models/category.py
finapi/models/category_list.py
finapi/models/category_params.py
finapi/models/change_client_credentials_params.py
finapi/models/check_categorization_data.py
finapi/models/check_categorization_transaction_data.py
finapi/models/clearing_account_data.py
finapi/models/client_configuration.py
finapi/models/client_configuration_params.py
finapi/models/daily_balance.py
finapi/models/daily_balance_list.py
finapi/models/direct_debit_ordering_response.py
finapi/models/edit_bank_connection_params.py
finapi/models/edit_category_params.py
finapi/models/error_details.py
finapi/models/error_message.py
finapi/models/execute_password_change_params.py
finapi/models/execute_sepa_direct_debit_params.py
finapi/models/execute_sepa_money_transfer_params.py
finapi/models/iban_rule.py
finapi/models/iban_rule_list.py
finapi/models/iban_rule_params.py
finapi/models/iban_rules_params.py
finapi/models/identifier_list.py
finapi-0.9.9.dist-info/METADATA
finapi-0.9.9.dist-info/WHEEL
finapi-0.9.9.dist-info/top_level.txt
finapi-0.9.9.dist-info/RECORD
