Metadata-Version: 2.1
Name: finapi
Version: 0.9.9
Summary: FinAPI RESTful Services
Home-page: UNKNOWN
Author: mishaker
Author-email: misagh.shakeri@gmail.com
License: UNKNOWN
Keywords: FinAPI,FinAPI RESTful Services
Platform: UNKNOWN
Requires-Dist: urllib3 (>=1.15)
Requires-Dist: six (>=1.10)
Requires-Dist: certifi
Requires-Dist: python-dateutil
